<xml xmlns:v="urn:schemas-microsoft-com:vml"
 xmlns:o="urn:schemas-microsoft-com:office:office"
 xmlns:p="urn:schemas-microsoft-com:office:powerpoint"
 xmlns:oa="urn:schemas-microsoft-com:office:activation">
 <o:shapelayout v:ext="edit">
  <o:idmap v:ext="edit" data="12"/>
  <o:rules v:ext="edit">
   <o:r id="V:Rule1" type="callout" idref="#AutoShape_x0020_150"/>
  </o:rules>
 </o:shapelayout><p:shaperange id="Picture_x0020_43">
  <v:shapetype id="_x0000_t75" coordsize="21600,21600" o:spt="75"
   o:preferrelative="t" path="m@4@5l@4@11@9@11@9@5xe" filled="f" stroked="f">
   <v:stroke joinstyle="miter"/>
   <v:formulas>
    <v:f eqn="if lineDrawn pixelLineWidth 0"/>
    <v:f eqn="sum @0 1 0"/>
    <v:f eqn="sum 0 0 @1"/>
    <v:f eqn="prod @2 1 2"/>
    <v:f eqn="prod @3 21600 pixelWidth"/>
    <v:f eqn="prod @3 21600 pixelHeight"/>
    <v:f eqn="sum @0 0 1"/>
    <v:f eqn="prod @6 1 2"/>
    <v:f eqn="prod @7 21600 pixelWidth"/>
    <v:f eqn="sum @8 21600 0"/>
    <v:f eqn="prod @7 21600 pixelHeight"/>
    <v:f eqn="sum @10 21600 0"/>
   </v:formulas>
   <v:path o:extrusionok="f" gradientshapeok="t" o:connecttype="rect"/>
   <o:lock v:ext="edit" aspectratio="t"/>
  </v:shapetype><v:shape id="Picture_x0020_43" o:spid="_x0000_s12290" type="#_x0000_t75"
   style='position:absolute;left:617.25pt;top:12pt;width:88.5pt;height:103.5pt;
   visibility:visible'>
   <v:imagedata src="slide0064_image001.png" o:title=""/>
  </v:shape></p:shaperange>
 <p:shaperange id="Text_x0020_Box_x0020_44">
  <v:shapetype id="_x0000_t202" coordsize="21600,21600" o:spt="202" path="m,l,21600r21600,l21600,xe">
   <v:stroke joinstyle="miter"/>
   <v:path gradientshapeok="t" o:connecttype="rect"/>
  </v:shapetype><v:shape id="Text_x0020_Box_x0020_44" o:spid="_x0000_s12291"
   type="#_x0000_t202" style='position:absolute;left:209.375pt;top:50.375pt;
   width:263.625pt;height:31.25pt;visibility:visible;mso-wrap-style:none'
   filled="f" stroked="f">
   <v:textbox style='mso-rotate-with-shape:t;mso-fit-shape-to-text:t'/>
  </v:shape><v:line id="Line_x0020_101" o:spid="_x0000_s12292" style='position:absolute;
   visibility:visible;mso-wrap-style:none;v-text-anchor:middle' from="110.25pt,304.5pt"
   to="606pt,304.5pt" strokecolor="#ddd"/>
 </p:shaperange>
 <p:shaperange id="Line_x0020_102">
  <v:line id="Line_x0020_102" o:spid="_x0000_s12293" style='position:absolute;
   visibility:visible;mso-wrap-style:none;v-text-anchor:middle' from="354pt,124.5pt"
   to="354pt,468.75pt" strokecolor="#ddd" strokeweight=".25pt"/>
 </p:shaperange>
 <p:shaperange id="Rectangle_x0020_103">
  <v:rect id="Rectangle_x0020_103" o:spid="_x0000_s12294" style='position:absolute;
   left:333pt;top:290.25pt;width:37.5pt;height:32.25pt;visibility:visible;
   mso-wrap-style:none;v-text-anchor:middle' fillcolor="white [0]" stroked="f">
   <v:textbox style='mso-rotate-with-shape:t'/>
  </v:rect><v:rect id="Rectangle_x0020_108" o:spid="_x0000_s12295" style='position:absolute;
   left:5.375pt;top:0;width:157.75pt;height:19.25pt;visibility:visible;
   mso-wrap-style:none' filled="f" stroked="f">
   <v:textbox style='mso-rotate-with-shape:t;mso-fit-shape-to-text:t'/>
  </v:rect></p:shaperange>
 <p:shaperange id="Line_x0020_109">
  <v:line id="Line_x0020_109" o:spid="_x0000_s12296" style='position:absolute;
   flip:y;visibility:visible;mso-wrap-style:none;v-text-anchor:middle' from="48.75pt,499.5pt"
   to="664.5pt,499.5pt" strokecolor="#ddd"/>
  <v:rect id="Rectangle_x0020_110" o:spid="_x0000_s12297" style='position:absolute;
   left:42.625pt;top:498pt;width:289.75pt;height:31.25pt;visibility:visible;
   mso-wrap-style:none;v-text-anchor:middle' filled="f" stroked="f">
   <v:textbox style='mso-rotate-with-shape:t;mso-fit-shape-to-text:t'/>
  </v:rect></p:shaperange>
 <p:shaperange id="Group_x0020_112">
  <v:group id="Group_x0020_112" o:spid="_x0000_s12299" style='position:absolute;
   left:293.125pt;top:247.125pt;width:16.75pt;height:32.625pt' coordorigin="2682,3010"
   coordsize="341,261">
   <v:shape id="Freeform_x0020_113" o:spid="_x0000_s12390" alt="Esferas"
    style='position:absolute;left:2682;top:3073;width:341;height:198;
    visibility:visible;mso-wrap-style:none;v-text-anchor:middle' coordsize="341,198"
    o:spt="100" adj="-11796480,,5400" path="m114,59v14,-1,3,-49,12,-54c135,,159,11,168,29v9,18,,75,12,84c192,122,223,87,240,83v17,-4,46,-5,42,6c278,100,210,139,216,149v6,10,89,-6,102,c331,155,341,179,294,185v-47,6,-222,13,-258,c,172,77,136,78,107,79,78,36,19,42,11v6,-8,58,49,72,48xe"
    fillcolor="#bbe0e3 [4]" stroked="f">
    <v:fill src="slide0053_image471.gif" o:title="" color2="white [0]" type="pattern"/>
    <v:stroke joinstyle="round"/>
    <v:formulas/>
    <v:path arrowok="t" o:connecttype="custom" o:connectlocs="114,59;126,5;168,29;180,113;240,83;282,89;216,149;318,149;294,185;36,185;78,107;42,11;114,59"
     o:connectangles="0,0,0,0,0,0,0,0,0,0,0,0,0" textboxrect="0,0,341,198"/>
    <v:textbox style='mso-rotate-with-shape:t'/>
   </v:shape><v:shape id="Freeform_x0020_114" o:spid="_x0000_s12391" style='position:absolute;
    left:2872;top:3010;width:56;height:76;visibility:visible;mso-wrap-style:none;
    v-text-anchor:middle' coordsize="56,76" o:spt="100" adj="-11796480,,5400"
    path="m8,38c8,26,,4,8,2,16,,56,14,56,26,56,38,16,72,8,74,,76,8,50,8,38xe"
    fillcolor="#bbe0e3 [4]" strokecolor="#bbe0e3 [4]">
    <v:stroke joinstyle="round"/>
    <v:formulas/>
    <v:path arrowok="t" o:connecttype="custom" o:connectlocs="8,38;8,2;56,26;8,74;8,38"
     o:connectangles="0,0,0,0,0" textboxrect="0,0,56,76"/>
    <v:textbox style='mso-rotate-with-shape:t'/>
   </v:shape><v:shape id="Freeform_x0020_115" o:spid="_x0000_s12392" style='position:absolute;
    left:2961;top:3033;width:55;height:83;visibility:visible;mso-wrap-style:none;
    v-text-anchor:middle' coordsize="133,113" o:spt="100" adj="-11796480,,5400"
    path="m69,27c85,10,89,,99,3v10,3,34,32,30,42c125,55,96,53,75,63,54,73,6,113,3,105,,97,53,44,69,27xe"
    fillcolor="#bbe0e3 [4]" strokecolor="#bbe0e3 [4]">
    <v:stroke joinstyle="round"/>
    <v:formulas/>
    <v:path arrowok="t" o:connecttype="custom" o:connectlocs="12,15;17,1;22,24;13,34;0,57;12,15"
     o:connectangles="0,0,0,0,0,0" textboxrect="0,0,133,113"/>
    <v:textbox style='mso-rotate-with-shape:t'/>
   </v:shape></v:group></p:shaperange>
 <p:shaperange id="Group_x0020_116">
  <v:group id="Group_x0020_116" o:spid="_x0000_s12300" style='position:absolute;
   left:249.625pt;top:197.875pt;width:39.75pt;height:46.125pt' coordorigin="1910,752"
   coordsize="811,369">
   <v:shape id="Freeform_x0020_117" o:spid="_x0000_s12386" style='position:absolute;
    left:1910;top:752;width:643;height:369;visibility:visible;mso-wrap-style:none;
    v-text-anchor:middle' coordsize="415,315" o:spt="100" adj="-11796480,,5400"
    path="m66,12c109,4,245,,300,12v55,12,80,45,96,72c412,111,395,153,396,174v1,21,5,19,6,36c403,227,415,264,402,276v-13,12,-65,39,-78,6c311,249,371,115,324,78,277,41,84,71,42,60,,49,23,20,66,12xe"
    fillcolor="#bbe0e3 [4]" stroked="f">
    <v:fill color2="#839c9e" focus="100%" type="gradient"/>
    <v:stroke joinstyle="round"/>
    <v:formulas/>
    <v:path arrowok="t" o:connecttype="custom" o:connectlocs="66,12;300,12;396,84;396,174;402,210;402,276;324,282;324,78;42,60;66,12"
     o:connectangles="0,0,0,0,0,0,0,0,0,0" textboxrect="0,0,415,315"/>
    <v:textbox style='mso-rotate-with-shape:t'/>
   </v:shape><v:shape id="Freeform_x0020_118" o:spid="_x0000_s12387" alt="Esferas"
    style='position:absolute;left:2380;top:917;width:341;height:198;
    visibility:visible;mso-wrap-style:none;v-text-anchor:middle' coordsize="341,198"
    o:spt="100" adj="-11796480,,5400" path="m114,59v14,-1,3,-49,12,-54c135,,159,11,168,29v9,18,,75,12,84c192,122,223,87,240,83v17,-4,46,-5,42,6c278,100,210,139,216,149v6,10,89,-6,102,c331,155,341,179,294,185v-47,6,-222,13,-258,c,172,77,136,78,107,79,78,36,19,42,11v6,-8,58,49,72,48xe"
    fillcolor="#bbe0e3 [4]" stroked="f">
    <v:fill src="slide0053_image471.gif" o:title="" color2="white [0]" type="pattern"/>
    <v:stroke joinstyle="round"/>
    <v:formulas/>
    <v:path arrowok="t" o:connecttype="custom" o:connectlocs="114,59;126,5;168,29;180,113;240,83;282,89;216,149;318,149;294,185;36,185;78,107;42,11;114,59"
     o:connectangles="0,0,0,0,0,0,0,0,0,0,0,0,0" textboxrect="0,0,341,198"/>
    <v:textbox style='mso-rotate-with-shape:t'/>
   </v:shape><v:shape id="Freeform_x0020_119" o:spid="_x0000_s12388" style='position:absolute;
    left:2570;top:854;width:56;height:76;visibility:visible;mso-wrap-style:none;
    v-text-anchor:middle' coordsize="56,76" o:spt="100" adj="-11796480,,5400"
    path="m8,38c8,26,,4,8,2,16,,56,14,56,26,56,38,16,72,8,74,,76,8,50,8,38xe"
    fillcolor="#bbe0e3 [4]" strokecolor="#bbe0e3 [4]">
    <v:stroke joinstyle="round"/>
    <v:formulas/>
    <v:path arrowok="t" o:connecttype="custom" o:connectlocs="8,38;8,2;56,26;8,74;8,38"
     o:connectangles="0,0,0,0,0" textboxrect="0,0,56,76"/>
    <v:textbox style='mso-rotate-with-shape:t'/>
   </v:shape><v:shape id="Freeform_x0020_120" o:spid="_x0000_s12389" style='position:absolute;
    left:2659;top:877;width:55;height:83;visibility:visible;mso-wrap-style:none;
    v-text-anchor:middle' coordsize="133,113" o:spt="100" adj="-11796480,,5400"
    path="m69,27c85,10,89,,99,3v10,3,34,32,30,42c125,55,96,53,75,63,54,73,6,113,3,105,,97,53,44,69,27xe"
    fillcolor="#bbe0e3 [4]" strokecolor="#bbe0e3 [4]">
    <v:stroke joinstyle="round"/>
    <v:formulas/>
    <v:path arrowok="t" o:connecttype="custom" o:connectlocs="12,15;17,1;22,24;13,34;0,57;12,15"
     o:connectangles="0,0,0,0,0,0" textboxrect="0,0,133,113"/>
    <v:textbox style='mso-rotate-with-shape:t'/>
   </v:shape></v:group></p:shaperange>
 <p:shaperange id="Group_x0020_121">
  <v:group id="Group_x0020_121" o:spid="_x0000_s12301" style='position:absolute;
   left:218.125pt;top:164.125pt;width:39.75pt;height:46.125pt' coordorigin="1910,752"
   coordsize="811,369">
   <v:shape id="Freeform_x0020_122" o:spid="_x0000_s12382" style='position:absolute;
    left:1910;top:752;width:643;height:369;visibility:visible;mso-wrap-style:none;
    v-text-anchor:middle' coordsize="415,315" o:spt="100" adj="-11796480,,5400"
    path="m66,12c109,4,245,,300,12v55,12,80,45,96,72c412,111,395,153,396,174v1,21,5,19,6,36c403,227,415,264,402,276v-13,12,-65,39,-78,6c311,249,371,115,324,78,277,41,84,71,42,60,,49,23,20,66,12xe"
    fillcolor="#bbe0e3 [4]" stroked="f">
    <v:fill color2="#839c9e" focus="100%" type="gradient"/>
    <v:stroke joinstyle="round"/>
    <v:formulas/>
    <v:path arrowok="t" o:connecttype="custom" o:connectlocs="66,12;300,12;396,84;396,174;402,210;402,276;324,282;324,78;42,60;66,12"
     o:connectangles="0,0,0,0,0,0,0,0,0,0" textboxrect="0,0,415,315"/>
    <v:textbox style='mso-rotate-with-shape:t'/>
   </v:shape><v:shape id="Freeform_x0020_123" o:spid="_x0000_s12383" alt="Esferas"
    style='position:absolute;left:2380;top:917;width:341;height:198;
    visibility:visible;mso-wrap-style:none;v-text-anchor:middle' coordsize="341,198"
    o:spt="100" adj="-11796480,,5400" path="m114,59v14,-1,3,-49,12,-54c135,,159,11,168,29v9,18,,75,12,84c192,122,223,87,240,83v17,-4,46,-5,42,6c278,100,210,139,216,149v6,10,89,-6,102,c331,155,341,179,294,185v-47,6,-222,13,-258,c,172,77,136,78,107,79,78,36,19,42,11v6,-8,58,49,72,48xe"
    fillcolor="#bbe0e3 [4]" stroked="f">
    <v:fill src="slide0053_image471.gif" o:title="" color2="white [0]" type="pattern"/>
    <v:stroke joinstyle="round"/>
    <v:formulas/>
    <v:path arrowok="t" o:connecttype="custom" o:connectlocs="114,59;126,5;168,29;180,113;240,83;282,89;216,149;318,149;294,185;36,185;78,107;42,11;114,59"
     o:connectangles="0,0,0,0,0,0,0,0,0,0,0,0,0" textboxrect="0,0,341,198"/>
    <v:textbox style='mso-rotate-with-shape:t'/>
   </v:shape><v:shape id="Freeform_x0020_124" o:spid="_x0000_s12384" style='position:absolute;
    left:2570;top:854;width:56;height:76;visibility:visible;mso-wrap-style:none;
    v-text-anchor:middle' coordsize="56,76" o:spt="100" adj="-11796480,,5400"
    path="m8,38c8,26,,4,8,2,16,,56,14,56,26,56,38,16,72,8,74,,76,8,50,8,38xe"
    fillcolor="#bbe0e3 [4]" strokecolor="#bbe0e3 [4]">
    <v:stroke joinstyle="round"/>
    <v:formulas/>
    <v:path arrowok="t" o:connecttype="custom" o:connectlocs="8,38;8,2;56,26;8,74;8,38"
     o:connectangles="0,0,0,0,0" textboxrect="0,0,56,76"/>
    <v:textbox style='mso-rotate-with-shape:t'/>
   </v:shape><v:shape id="Freeform_x0020_125" o:spid="_x0000_s12385" style='position:absolute;
    left:2659;top:877;width:55;height:83;visibility:visible;mso-wrap-style:none;
    v-text-anchor:middle' coordsize="133,113" o:spt="100" adj="-11796480,,5400"
    path="m69,27c85,10,89,,99,3v10,3,34,32,30,42c125,55,96,53,75,63,54,73,6,113,3,105,,97,53,44,69,27xe"
    fillcolor="#bbe0e3 [4]" strokecolor="#bbe0e3 [4]">
    <v:stroke joinstyle="round"/>
    <v:formulas/>
    <v:path arrowok="t" o:connecttype="custom" o:connectlocs="12,15;17,1;22,24;13,34;0,57;12,15"
     o:connectangles="0,0,0,0,0,0" textboxrect="0,0,133,113"/>
    <v:textbox style='mso-rotate-with-shape:t'/>
   </v:shape></v:group></p:shaperange>
 <p:shaperange id="Group_x0020_126">
  <v:group id="Group_x0020_126" o:spid="_x0000_s12302" style='position:absolute;
   left:185.875pt;top:128.125pt;width:39.75pt;height:46.125pt' coordorigin="1910,752"
   coordsize="811,369">
   <v:shape id="Freeform_x0020_127" o:spid="_x0000_s12378" style='position:absolute;
    left:1910;top:752;width:643;height:369;visibility:visible;mso-wrap-style:none;
    v-text-anchor:middle' coordsize="415,315" o:spt="100" adj="-11796480,,5400"
    path="m66,12c109,4,245,,300,12v55,12,80,45,96,72c412,111,395,153,396,174v1,21,5,19,6,36c403,227,415,264,402,276v-13,12,-65,39,-78,6c311,249,371,115,324,78,277,41,84,71,42,60,,49,23,20,66,12xe"
    fillcolor="#bbe0e3 [4]" stroked="f">
    <v:fill color2="#839c9e" focus="100%" type="gradient"/>
    <v:stroke joinstyle="round"/>
    <v:formulas/>
    <v:path arrowok="t" o:connecttype="custom" o:connectlocs="66,12;300,12;396,84;396,174;402,210;402,276;324,282;324,78;42,60;66,12"
     o:connectangles="0,0,0,0,0,0,0,0,0,0" textboxrect="0,0,415,315"/>
    <v:textbox style='mso-rotate-with-shape:t'/>
   </v:shape><v:shape id="Freeform_x0020_128" o:spid="_x0000_s12379" alt="Esferas"
    style='position:absolute;left:2380;top:917;width:341;height:198;
    visibility:visible;mso-wrap-style:none;v-text-anchor:middle' coordsize="341,198"
    o:spt="100" adj="-11796480,,5400" path="m114,59v14,-1,3,-49,12,-54c135,,159,11,168,29v9,18,,75,12,84c192,122,223,87,240,83v17,-4,46,-5,42,6c278,100,210,139,216,149v6,10,89,-6,102,c331,155,341,179,294,185v-47,6,-222,13,-258,c,172,77,136,78,107,79,78,36,19,42,11v6,-8,58,49,72,48xe"
    fillcolor="#bbe0e3 [4]" stroked="f">
    <v:fill src="slide0053_image471.gif" o:title="" color2="white [0]" type="pattern"/>
    <v:stroke joinstyle="round"/>
    <v:formulas/>
    <v:path arrowok="t" o:connecttype="custom" o:connectlocs="114,59;126,5;168,29;180,113;240,83;282,89;216,149;318,149;294,185;36,185;78,107;42,11;114,59"
     o:connectangles="0,0,0,0,0,0,0,0,0,0,0,0,0" textboxrect="0,0,341,198"/>
    <v:textbox style='mso-rotate-with-shape:t'/>
   </v:shape><v:shape id="Freeform_x0020_129" o:spid="_x0000_s12380" style='position:absolute;
    left:2570;top:854;width:56;height:76;visibility:visible;mso-wrap-style:none;
    v-text-anchor:middle' coordsize="56,76" o:spt="100" adj="-11796480,,5400"
    path="m8,38c8,26,,4,8,2,16,,56,14,56,26,56,38,16,72,8,74,,76,8,50,8,38xe"
    fillcolor="#bbe0e3 [4]" strokecolor="#bbe0e3 [4]">
    <v:stroke joinstyle="round"/>
    <v:formulas/>
    <v:path arrowok="t" o:connecttype="custom" o:connectlocs="8,38;8,2;56,26;8,74;8,38"
     o:connectangles="0,0,0,0,0" textboxrect="0,0,56,76"/>
    <v:textbox style='mso-rotate-with-shape:t'/>
   </v:shape><v:shape id="Freeform_x0020_130" o:spid="_x0000_s12381" style='position:absolute;
    left:2659;top:877;width:55;height:83;visibility:visible;mso-wrap-style:none;
    v-text-anchor:middle' coordsize="133,113" o:spt="100" adj="-11796480,,5400"
    path="m69,27c85,10,89,,99,3v10,3,34,32,30,42c125,55,96,53,75,63,54,73,6,113,3,105,,97,53,44,69,27xe"
    fillcolor="#bbe0e3 [4]" strokecolor="#bbe0e3 [4]">
    <v:stroke joinstyle="round"/>
    <v:formulas/>
    <v:path arrowok="t" o:connecttype="custom" o:connectlocs="12,15;17,1;22,24;13,34;0,57;12,15"
     o:connectangles="0,0,0,0,0,0" textboxrect="0,0,133,113"/>
    <v:textbox style='mso-rotate-with-shape:t'/>
   </v:shape></v:group></p:shaperange>
 <p:shaperange id="Group_x0020_131">
  <v:group id="Group_x0020_131" o:spid="_x0000_s12303" style='position:absolute;
   left:156.125pt;top:94.625pt;width:39.75pt;height:46.125pt' coordorigin="1910,752"
   coordsize="811,369">
   <v:shape id="Freeform_x0020_132" o:spid="_x0000_s12374" style='position:absolute;
    left:1910;top:752;width:643;height:369;visibility:visible;mso-wrap-style:none;
    v-text-anchor:middle' coordsize="415,315" o:spt="100" adj="-11796480,,5400"
    path="m66,12c109,4,245,,300,12v55,12,80,45,96,72c412,111,395,153,396,174v1,21,5,19,6,36c403,227,415,264,402,276v-13,12,-65,39,-78,6c311,249,371,115,324,78,277,41,84,71,42,60,,49,23,20,66,12xe"
    fillcolor="#bbe0e3 [4]" stroked="f">
    <v:fill color2="#839c9e" focus="100%" type="gradient"/>
    <v:stroke joinstyle="round"/>
    <v:formulas/>
    <v:path arrowok="t" o:connecttype="custom" o:connectlocs="66,12;300,12;396,84;396,174;402,210;402,276;324,282;324,78;42,60;66,12"
     o:connectangles="0,0,0,0,0,0,0,0,0,0" textboxrect="0,0,415,315"/>
    <v:textbox style='mso-rotate-with-shape:t'/>
   </v:shape><v:shape id="Freeform_x0020_133" o:spid="_x0000_s12375" alt="Esferas"
    style='position:absolute;left:2380;top:917;width:341;height:198;
    visibility:visible;mso-wrap-style:none;v-text-anchor:middle' coordsize="341,198"
    o:spt="100" adj="-11796480,,5400" path="m114,59v14,-1,3,-49,12,-54c135,,159,11,168,29v9,18,,75,12,84c192,122,223,87,240,83v17,-4,46,-5,42,6c278,100,210,139,216,149v6,10,89,-6,102,c331,155,341,179,294,185v-47,6,-222,13,-258,c,172,77,136,78,107,79,78,36,19,42,11v6,-8,58,49,72,48xe"
    fillcolor="#bbe0e3 [4]" stroked="f">
    <v:fill src="slide0053_image471.gif" o:title="" color2="white [0]" type="pattern"/>
    <v:stroke joinstyle="round"/>
    <v:formulas/>
    <v:path arrowok="t" o:connecttype="custom" o:connectlocs="114,59;126,5;168,29;180,113;240,83;282,89;216,149;318,149;294,185;36,185;78,107;42,11;114,59"
     o:connectangles="0,0,0,0,0,0,0,0,0,0,0,0,0" textboxrect="0,0,341,198"/>
    <v:textbox style='mso-rotate-with-shape:t'/>
   </v:shape><v:shape id="Freeform_x0020_134" o:spid="_x0000_s12376" style='position:absolute;
    left:2570;top:854;width:56;height:76;visibility:visible;mso-wrap-style:none;
    v-text-anchor:middle' coordsize="56,76" o:spt="100" adj="-11796480,,5400"
    path="m8,38c8,26,,4,8,2,16,,56,14,56,26,56,38,16,72,8,74,,76,8,50,8,38xe"
    fillcolor="#bbe0e3 [4]" strokecolor="#bbe0e3 [4]">
    <v:stroke joinstyle="round"/>
    <v:formulas/>
    <v:path arrowok="t" o:connecttype="custom" o:connectlocs="8,38;8,2;56,26;8,74;8,38"
     o:connectangles="0,0,0,0,0" textboxrect="0,0,56,76"/>
    <v:textbox style='mso-rotate-with-shape:t'/>
   </v:shape><v:shape id="Freeform_x0020_135" o:spid="_x0000_s12377" style='position:absolute;
    left:2659;top:877;width:55;height:83;visibility:visible;mso-wrap-style:none;
    v-text-anchor:middle' coordsize="133,113" o:spt="100" adj="-11796480,,5400"
    path="m69,27c85,10,89,,99,3v10,3,34,32,30,42c125,55,96,53,75,63,54,73,6,113,3,105,,97,53,44,69,27xe"
    fillcolor="#bbe0e3 [4]" strokecolor="#bbe0e3 [4]">
    <v:stroke joinstyle="round"/>
    <v:formulas/>
    <v:path arrowok="t" o:connecttype="custom" o:connectlocs="12,15;17,1;22,24;13,34;0,57;12,15"
     o:connectangles="0,0,0,0,0,0" textboxrect="0,0,133,113"/>
    <v:textbox style='mso-rotate-with-shape:t'/>
   </v:shape></v:group></p:shaperange>
 <p:shaperange id="AutoShape_x0020_136">
  <v:shapetype id="_x0000_t176" coordsize="21600,21600" o:spt="176" adj="2700"
   path="m@0,qx0@0l0@2qy@0,21600l@1,21600qx21600@2l21600@0qy@1,xe">
   <v:stroke joinstyle="miter"/>
   <v:formulas>
    <v:f eqn="val #0"/>
    <v:f eqn="sum width 0 #0"/>
    <v:f eqn="sum height 0 #0"/>
    <v:f eqn="prod @0 2929 10000"/>
    <v:f eqn="sum width 0 @3"/>
    <v:f eqn="sum height 0 @3"/>
    <v:f eqn="val width"/>
    <v:f eqn="val height"/>
    <v:f eqn="prod width 1 2"/>
    <v:f eqn="prod height 1 2"/>
   </v:formulas>
   <v:path gradientshapeok="t" limo="10800,10800" o:connecttype="custom"
    o:connectlocs="@8,0;0,@9;@8,@7;@6,@9" textboxrect="@3,@3,@4,@5"/>
  </v:shapetype><v:shape id="AutoShape_x0020_136" o:spid="_x0000_s12304"
   type="#_x0000_t176" style='position:absolute;left:152.125pt;top:101.125pt;
   width:30.25pt;height:18.75pt;visibility:visible;mso-wrap-style:none;
   v-text-anchor:middle' fillcolor="#fcf" stroked="f">
   <v:textbox style='mso-rotate-with-shape:t'/>
  </v:shape><v:shape id="Text_x0020_Box_x0020_137" o:spid="_x0000_s12305"
   type="#_x0000_t202" style='position:absolute;left:135.125pt;top:100pt;
   width:74pt;height:18pt;visibility:visible;mso-wrap-style:none' filled="f"
   stroked="f">
   <v:textbox style='mso-rotate-with-shape:t;mso-fit-shape-to-text:t'/>
  </v:shape></p:shaperange>
 <p:shaperange id="AutoShape_x0020_138">
  <v:shape id="AutoShape_x0020_138" o:spid="_x0000_s12306" type="#_x0000_t176"
   style='position:absolute;left:181.875pt;top:136.125pt;width:30.25pt;
   height:18.75pt;visibility:visible;mso-wrap-style:none;v-text-anchor:middle'
   fillcolor="#ff9" stroked="f">
   <v:textbox style='mso-rotate-with-shape:t'/>
  </v:shape><v:shape id="Text_x0020_Box_x0020_139" o:spid="_x0000_s12307"
   type="#_x0000_t202" style='position:absolute;left:176.625pt;top:136.5pt;
   width:41pt;height:18pt;visibility:visible;mso-wrap-style:none' filled="f"
   stroked="f">
   <v:textbox style='mso-rotate-with-shape:t;mso-fit-shape-to-text:t'/>
  </v:shape></p:shaperange>
 <p:shaperange id="AutoShape_x0020_140">
  <v:shape id="AutoShape_x0020_140" o:spid="_x0000_s12308" type="#_x0000_t176"
   style='position:absolute;left:211.875pt;top:172.875pt;width:30.25pt;
   height:18.75pt;visibility:visible;mso-wrap-style:none;v-text-anchor:middle'
   fillcolor="#ffeb97" stroked="f">
   <v:textbox style='mso-rotate-with-shape:t'/>
  </v:shape><v:shape id="Text_x0020_Box_x0020_141" o:spid="_x0000_s12309"
   type="#_x0000_t202" style='position:absolute;left:192.875pt;top:173.25pt;
   width:61.5pt;height:18pt;visibility:visible;mso-wrap-style:none' filled="f"
   stroked="f">
   <v:textbox style='mso-rotate-with-shape:t;mso-fit-shape-to-text:t'/>
  </v:shape></p:shaperange>
 <p:shaperange id="AutoShape_x0020_142">
  <v:shape id="AutoShape_x0020_142" o:spid="_x0000_s12310" type="#_x0000_t176"
   style='position:absolute;left:242.625pt;top:205.875pt;width:30.25pt;
   height:18.75pt;visibility:visible;mso-wrap-style:none;v-text-anchor:middle'
   fillcolor="#cfc" stroked="f">
   <v:textbox style='mso-rotate-with-shape:t'/>
  </v:shape><v:shape id="Text_x0020_Box_x0020_143" o:spid="_x0000_s12311"
   type="#_x0000_t202" style='position:absolute;left:233.25pt;top:205.5pt;
   width:47pt;height:18pt;visibility:visible;mso-wrap-style:none' filled="f"
   stroked="f">
   <v:textbox style='mso-rotate-with-shape:t;mso-fit-shape-to-text:t'/>
  </v:shape></p:shaperange>
 <p:shaperange id="AutoShape_x0020_144">
  <v:shape id="AutoShape_x0020_144" o:spid="_x0000_s12312" type="#_x0000_t176"
   style='position:absolute;left:268.125pt;top:238.875pt;width:30.25pt;
   height:18.75pt;visibility:visible;mso-wrap-style:none;v-text-anchor:middle'
   fillcolor="#ffe7e1" stroked="f">
   <v:textbox style='mso-rotate-with-shape:t'/>
  </v:shape><v:shape id="Text_x0020_Box_x0020_145" o:spid="_x0000_s12313"
   type="#_x0000_t202" style='position:absolute;left:247.875pt;top:239.25pt;
   width:73.5pt;height:18pt;visibility:visible;mso-wrap-style:none' filled="f"
   stroked="f">
   <v:textbox style='mso-rotate-with-shape:t;mso-fit-shape-to-text:t'/>
  </v:shape></p:shaperange>
 <p:shaperange id="Oval_x0020_146">
  <v:oval id="Oval_x0020_146" o:spid="_x0000_s12314" style='position:absolute;
   left:291.625pt;top:269.125pt;width:24.75pt;height:25.5pt;visibility:visible;
   mso-wrap-style:none;v-text-anchor:middle' fillcolor="#e0e0e0" strokecolor="#d7d7d7">
   <v:textbox style='mso-rotate-with-shape:t'/>
  </v:oval></p:shaperange>
 <p:shaperange id="Oval_x0020_147">
  <v:oval id="Oval_x0020_147" o:spid="_x0000_s12315" style='position:absolute;
   left:300.625pt;top:277.375pt;width:6.875pt;height:8.25pt;visibility:visible;
   mso-wrap-style:none;v-text-anchor:middle' fillcolor="white [0]"
   strokecolor="silver">
   <v:textbox style='mso-rotate-with-shape:t'/>
  </v:oval><v:shape id="Text_x0020_Box_x0020_148" o:spid="_x0000_s12316"
   type="#_x0000_t202" style='position:absolute;left:278.625pt;top:265.25pt;
   width:50.5pt;height:18pt;visibility:visible;mso-wrap-style:none' filled="f"
   stroked="f">
   <v:textbox style='mso-rotate-with-shape:t;mso-fit-shape-to-text:t'/>
  </v:shape><v:rect id="Rectangle_x0020_149" o:spid="_x0000_s12317" style='position:absolute;
   left:289pt;top:280.75pt;width:31pt;height:18pt;visibility:visible;
   mso-wrap-style:none' filled="f" stroked="f">
   <v:textbox style='mso-rotate-with-shape:t;mso-fit-shape-to-text:t'/>
  </v:rect></p:shaperange>
 <p:shaperange id="AutoShape_x0020_150">
  <v:shapetype id="_x0000_t62" coordsize="21600,21600" o:spt="62" adj="1350,25920"
   path="m3600,qx,3600l0@8@12@24,0@9,,18000qy3600,21600l@6,21600@15@27@7,21600,18000,21600qx21600,18000l21600@9@18@30,21600@8,21600,3600qy18000,l@7,0@21@33@6,xe">
   <v:stroke joinstyle="miter"/>
   <v:formulas>
    <v:f eqn="sum 10800 0 #0"/>
    <v:f eqn="sum 10800 0 #1"/>
    <v:f eqn="sum #0 0 #1"/>
    <v:f eqn="sum @0 @1 0"/>
    <v:f eqn="sum 21600 0 #0"/>
    <v:f eqn="sum 21600 0 #1"/>
    <v:f eqn="if @0 3600 12600"/>
    <v:f eqn="if @0 9000 18000"/>
    <v:f eqn="if @1 3600 12600"/>
    <v:f eqn="if @1 9000 18000"/>
    <v:f eqn="if @2 0 #0"/>
    <v:f eqn="if @3 @10 0"/>
    <v:f eqn="if #0 0 @11"/>
    <v:f eqn="if @2 @6 #0"/>
    <v:f eqn="if @3 @6 @13"/>
    <v:f eqn="if @5 @6 @14"/>
    <v:f eqn="if @2 #0 21600"/>
    <v:f eqn="if @3 21600 @16"/>
    <v:f eqn="if @4 21600 @17"/>
    <v:f eqn="if @2 #0 @6"/>
    <v:f eqn="if @3 @19 @6"/>
    <v:f eqn="if #1 @6 @20"/>
    <v:f eqn="if @2 @8 #1"/>
    <v:f eqn="if @3 @22 @8"/>
    <v:f eqn="if #0 @8 @23"/>
    <v:f eqn="if @2 21600 #1"/>
    <v:f eqn="if @3 21600 @25"/>
    <v:f eqn="if @5 21600 @26"/>
    <v:f eqn="if @2 #1 @8"/>
    <v:f eqn="if @3 @8 @28"/>
    <v:f eqn="if @4 @8 @29"/>
    <v:f eqn="if @2 #1 0"/>
    <v:f eqn="if @3 @31 0"/>
    <v:f eqn="if #1 0 @32"/>
    <v:f eqn="val #0"/>
    <v:f eqn="val #1"/>
   </v:formulas>
   <v:path o:connecttype="custom" o:connectlocs="10800,0;0,10800;10800,21600;21600,10800;@34,@35"
    textboxrect="791,791,20809,20809"/>
   <v:handles>
    <v:h position="#0,#1"/>
   </v:handles>
  </v:shapetype><v:shape id="AutoShape_x0020_150" o:spid="_x0000_s12318"
   type="#_x0000_t62" style='position:absolute;left:445.5pt;top:93.75pt;
   width:61.5pt;height:28.5pt;visibility:visible;v-text-anchor:middle' adj="3951,24253"
   fillcolor="#ffc" strokecolor="#d7d7d7">
   <v:textbox style='mso-rotate-with-shape:t'/>
  </v:shape><v:shape id="Text_x0020_Box_x0020_151" o:spid="_x0000_s12319"
   type="#_x0000_t202" style='position:absolute;left:440.75pt;top:98.625pt;
   width:71pt;height:18pt;visibility:visible;mso-wrap-style:none' filled="f"
   stroked="f">
   <v:textbox style='mso-rotate-with-shape:t;mso-fit-shape-to-text:t'/>
  </v:shape><v:shapetype id="_x0000_t103" coordsize="21600,21600" o:spt="103"
   adj="12960,19440,7200" path="wr@22,0@21@3,,0@21@4@22@14@21@1@21@7@2@12l@2@13,0@8@2@11at@22,0@21@3@2@10@24@16@22@14@21@1@24@16,0@14xear@22@14@21@1@21@7@24@16nfe">
   <v:stroke joinstyle="miter"/>
   <v:formulas>
    <v:f eqn="val #0"/>
    <v:f eqn="val #1"/>
    <v:f eqn="val #2"/>
    <v:f eqn="sum #0 width #1"/>
    <v:f eqn="prod @3 1 2"/>
    <v:f eqn="sum #1 #1 width"/>
    <v:f eqn="sum @5 #1 #0"/>
    <v:f eqn="prod @6 1 2"/>
    <v:f eqn="mid width #0"/>
    <v:f eqn="ellipse #2 height @4"/>
    <v:f eqn="sum @4 @9 0"/>
    <v:f eqn="sum @10 #1 width"/>
    <v:f eqn="sum @7 @9 0"/>
    <v:f eqn="sum @11 width #0"/>
    <v:f eqn="sum @5 0 #0"/>
    <v:f eqn="prod @14 1 2"/>
    <v:f eqn="mid @4 @7"/>
    <v:f eqn="sum #0 #1 width"/>
    <v:f eqn="prod @17 1 2"/>
    <v:f eqn="sum @16 0 @18"/>
    <v:f eqn="val width"/>
    <v:f eqn="val height"/>
    <v:f eqn="sum 0 0 height"/>
    <v:f eqn="sum @16 0 @4"/>
    <v:f eqn="ellipse @23 @4 height"/>
    <v:f eqn="sum @8 128 0"/>
    <v:f eqn="prod @5 1 2"/>
    <v:f eqn="sum @5 0 128"/>
    <v:f eqn="sum #0 @16 @11"/>
    <v:f eqn="sum width 0 #0"/>
    <v:f eqn="prod @29 1 2"/>
    <v:f eqn="prod height height 1"/>
    <v:f eqn="prod #2 #2 1"/>
    <v:f eqn="sum @31 0 @32"/>
    <v:f eqn="sqrt @33"/>
    <v:f eqn="sum @34 height 0"/>
    <v:f eqn="prod width height @35"/>
    <v:f eqn="sum @36 64 0"/>
    <v:f eqn="prod #0 1 2"/>
    <v:f eqn="ellipse @30 @38 height"/>
    <v:f eqn="sum @39 0 64"/>
    <v:f eqn="prod @4 1 2"/>
    <v:f eqn="sum #1 0 @41"/>
    <v:f eqn="prod height 4390 32768"/>
    <v:f eqn="prod height 28378 32768"/>
   </v:formulas>
   <v:path o:extrusionok="f" o:connecttype="custom" o:connectlocs="0,@15;@2,@11;0,@8;@2,@13;@21,@16"
    o:connectangles="180,180,180,90,0" textboxrect="@43,@41,@44,@42"/>
   <v:handles>
    <v:h position="topLeft,#0" yrange="@37,@27"/>
    <v:h position="topLeft,#1" yrange="@25,@20"/>
    <v:h position="#2,bottomRight" xrange="0,@40"/>
   </v:handles>
   <o:complex v:ext="view"/>
  </v:shapetype><v:shape id="AutoShape_x0020_152" o:spid="_x0000_s12320"
   type="#_x0000_t103" style='position:absolute;left:475.5pt;top:156pt;width:50.25pt;
   height:64.5pt;visibility:visible;mso-wrap-style:none;v-text-anchor:middle'
   fillcolor="#cfc" strokecolor="#d7d7d7">
   <v:textbox style='mso-rotate-with-shape:t'/>
  </v:shape><v:shape id="AutoShape_x0020_153" o:spid="_x0000_s12321" type="#_x0000_t103"
   style='position:absolute;left:419.75pt;top:150.5pt;width:50.25pt;height:65.25pt;
   rotation:180;visibility:visible;mso-wrap-style:none;v-text-anchor:middle'
   adj="12976,19465" fillcolor="#cfc" strokecolor="#d7d7d7">
   <v:textbox style='mso-rotate-with-shape:t'/>
  </v:shape><v:shape id="Text_x0020_Box_x0020_154" o:spid="_x0000_s12322"
   type="#_x0000_t202" style='position:absolute;left:418.875pt;top:165.375pt;
   width:107pt;height:28.75pt;visibility:visible;mso-wrap-style:none' filled="f"
   stroked="f">
   <v:textbox style='mso-rotate-with-shape:t;mso-fit-shape-to-text:t'/>
  </v:shape><v:shapetype id="_x0000_t13" coordsize="21600,21600" o:spt="13"
   adj="16200,5400" path="m@0,l@0@1,0@1,0@2@0@2@0,21600,21600,10800xe">
   <v:stroke joinstyle="miter"/>
   <v:formulas>
    <v:f eqn="val #0"/>
    <v:f eqn="val #1"/>
    <v:f eqn="sum height 0 #1"/>
    <v:f eqn="sum 10800 0 #1"/>
    <v:f eqn="sum width 0 #0"/>
    <v:f eqn="prod @4 @3 10800"/>
    <v:f eqn="sum width 0 @5"/>
   </v:formulas>
   <v:path o:connecttype="custom" o:connectlocs="@0,0;0,10800;@0,21600;21600,10800"
    o:connectangles="270,180,90,0" textboxrect="0,@1,@6,@2"/>
   <v:handles>
    <v:h position="#0,#1" xrange="0,21600" yrange="0,10800"/>
   </v:handles>
  </v:shapetype><v:shape id="AutoShape_x0020_155" o:spid="_x0000_s12323"
   type="#_x0000_t13" style='position:absolute;left:460.875pt;top:135.375pt;
   width:21.75pt;height:9pt;rotation:90;visibility:visible;mso-wrap-style:none;
   v-text-anchor:middle' fillcolor="#ffe579" stroked="f">
   <v:textbox style='mso-rotate-with-shape:t'/>
  </v:shape><v:oval id="Oval_x0020_156" o:spid="_x0000_s12324" style='position:absolute;
   left:464.25pt;top:245.25pt;width:24.75pt;height:25.5pt;visibility:visible;
   mso-wrap-style:none;v-text-anchor:middle' fillcolor="#e0e0e0" strokecolor="#d7d7d7">
   <v:textbox style='mso-rotate-with-shape:t'/>
  </v:oval></p:shaperange>
 <p:shaperange id="Oval_x0020_157">
  <v:oval id="Oval_x0020_157" o:spid="_x0000_s12325" style='position:absolute;
   left:473.25pt;top:253.5pt;width:6.875pt;height:8.25pt;visibility:visible;
   mso-wrap-style:none;v-text-anchor:middle' fillcolor="white [0]"
   strokecolor="silver">
   <v:textbox style='mso-rotate-with-shape:t'/>
  </v:oval><v:shape id="Text_x0020_Box_x0020_158" o:spid="_x0000_s12326"
   type="#_x0000_t202" style='position:absolute;left:452pt;top:241.375pt;
   width:50.5pt;height:18pt;visibility:visible;mso-wrap-style:none' filled="f"
   stroked="f">
   <v:textbox style='mso-rotate-with-shape:t;mso-fit-shape-to-text:t'/>
  </v:shape><v:rect id="Rectangle_x0020_159" o:spid="_x0000_s12327" style='position:absolute;
   left:461.625pt;top:256.875pt;width:31pt;height:18pt;visibility:visible;
   mso-wrap-style:none' filled="f" stroked="f">
   <v:textbox style='mso-rotate-with-shape:t;mso-fit-shape-to-text:t'/>
  </v:rect><v:shape id="AutoShape_x0020_160" o:spid="_x0000_s12328" type="#_x0000_t13"
   style='position:absolute;left:464.5pt;top:226.75pt;width:21.75pt;height:9pt;
   rotation:90;visibility:visible;mso-wrap-style:none;v-text-anchor:middle'
   fillcolor="#ffe579" stroked="f">
   <v:textbox style='mso-rotate-with-shape:t'/>
  </v:shape></p:shaperange>
 <p:shaperange id="AutoShape_x0020_161">
  <v:shapetype id="_x0000_t72" coordsize="21600,21600" o:spt="72" path="m11462,4342l9722,1887,8550,6382,4502,3625r870,4192l1172,8270r2763,3322l,12877r3330,2493l1285,17825r3520,415l4917,21600,7527,18125r1173,1587l9872,17370r1740,1472l12180,15935r2762,1435l14640,14350r4237,1282l16380,12310r1890,-1020l16985,9402,21600,6645,16380,6532,18007,3172,14525,5777,14790,xe">
   <v:stroke joinstyle="miter"/>
   <v:path gradientshapeok="t" o:connecttype="custom" o:connectlocs="9722,1887;0,12877;11612,18842;21600,6645"
    o:connectangles="270,180,90,0" textboxrect="5372,6382,14640,15935"/>
  </v:shapetype><v:shape id="AutoShape_x0020_161" o:spid="_x0000_s12329"
   type="#_x0000_t72" style='position:absolute;left:141pt;top:346.5pt;width:112.5pt;
   height:70.5pt;visibility:visible;mso-wrap-style:none;v-text-anchor:middle'
   fillcolor="#cfc" strokecolor="#e0e0e0">
   <v:textbox style='mso-rotate-with-shape:t'/>
  </v:shape><v:shape id="Text_x0020_Box_x0020_162" o:spid="_x0000_s12330"
   type="#_x0000_t202" style='position:absolute;left:165.875pt;top:371.625pt;
   width:56.5pt;height:18pt;visibility:visible;mso-wrap-style:none' filled="f"
   stroked="f">
   <v:textbox style='mso-rotate-with-shape:t;mso-fit-shape-to-text:t'/>
  </v:shape><v:shape id="Text_x0020_Box_x0020_163" o:spid="_x0000_s12331"
   type="#_x0000_t202" style='position:absolute;left:294.75pt;top:340.625pt;
   width:25.625pt;height:31.25pt;visibility:visible;mso-wrap-style:none'
   filled="f" stroked="f">
   <v:textbox style='mso-rotate-with-shape:t;mso-fit-shape-to-text:t'/>
  </v:shape><v:shape id="AutoShape_x0020_164" o:spid="_x0000_s12332" type="#_x0000_t13"
   style='position:absolute;left:258pt;top:364.5pt;width:32.25pt;height:7pt;
   rotation:-1916852fd;visibility:visible;mso-wrap-style:none;v-text-anchor:middle'
   fillcolor="#ffeb97" strokecolor="#e0e0e0">
   <v:textbox style='mso-rotate-with-shape:t'/>
  </v:shape><v:shape id="AutoShape_x0020_165" o:spid="_x0000_s12333" type="#_x0000_t13"
   style='position:absolute;left:257.75pt;top:386.75pt;width:32.25pt;height:7pt;
   rotation:1811404fd;visibility:visible;mso-wrap-style:none;v-text-anchor:middle'
   fillcolor="#ffeb97" strokecolor="#e0e0e0">
   <v:textbox style='mso-rotate-with-shape:t'/>
  </v:shape><v:shape id="Text_x0020_Box_x0020_166" o:spid="_x0000_s12334"
   type="#_x0000_t202" style='position:absolute;left:262.375pt;top:369.125pt;
   width:28pt;height:18pt;visibility:visible;mso-wrap-style:none' filled="f"
   stroked="f">
   <v:textbox style='mso-rotate-with-shape:t;mso-fit-shape-to-text:t'/>
  </v:shape><v:oval id="Oval_x0020_167" o:spid="_x0000_s12335" style='position:absolute;
   left:297pt;top:384pt;width:24.75pt;height:25.5pt;visibility:visible;
   mso-wrap-style:none;v-text-anchor:middle' fillcolor="#e0e0e0" strokecolor="#d7d7d7">
   <v:textbox style='mso-rotate-with-shape:t'/>
  </v:oval></p:shaperange>
 <p:shaperange id="Oval_x0020_168">
  <v:oval id="Oval_x0020_168" o:spid="_x0000_s12336" style='position:absolute;
   left:306pt;top:392.25pt;width:6.875pt;height:8.25pt;visibility:visible;
   mso-wrap-style:none;v-text-anchor:middle' fillcolor="white [0]"
   strokecolor="silver">
   <v:textbox style='mso-rotate-with-shape:t'/>
  </v:oval><v:shape id="Text_x0020_Box_x0020_169" o:spid="_x0000_s12337"
   type="#_x0000_t202" style='position:absolute;left:284pt;top:380.125pt;
   width:50.5pt;height:18pt;visibility:visible;mso-wrap-style:none' filled="f"
   stroked="f">
   <v:textbox style='mso-rotate-with-shape:t;mso-fit-shape-to-text:t'/>
  </v:shape><v:rect id="Rectangle_x0020_170" o:spid="_x0000_s12338" style='position:absolute;
   left:294.375pt;top:395.625pt;width:31pt;height:18pt;visibility:visible;
   mso-wrap-style:none' filled="f" stroked="f">
   <v:textbox style='mso-rotate-with-shape:t;mso-fit-shape-to-text:t'/>
  </v:rect></p:shaperange>
 <p:shaperange id="Line_x0020_171">
  <v:line id="Line_x0020_171" o:spid="_x0000_s12339" style='position:absolute;
   flip:x;visibility:visible;mso-wrap-style:none;v-text-anchor:middle' from="497.25pt,309pt"
   to="497.25pt,453.75pt" strokecolor="#963"/>
 </p:shaperange>
 <p:shaperange id="Line_x0020_172">
  <v:line id="Line_x0020_172" o:spid="_x0000_s12340" style='position:absolute;
   visibility:visible;mso-wrap-style:none;v-text-anchor:middle' from="408.75pt,384.75pt"
   to="587.25pt,384.75pt" strokecolor="#963"/>
 </p:shaperange>
 <p:shaperange id="Freeform_x0020_173">
  <v:shape id="Freeform_x0020_173" o:spid="_x0000_s12341" style='position:absolute;
   left:497.25pt;top:385.5pt;width:27pt;height:21.75pt;visibility:visible;
   mso-wrap-style:none;v-text-anchor:middle' coordsize="264,174" o:spt="100"
   adj="-11796480,,5400" path="m264,v-5,25,-9,51,-24,72c225,93,198,112,174,126v-24,14,-49,22,-78,30c67,164,21,171,,174e"
   filled="f" strokecolor="#66f">
   <v:stroke endarrow="open" joinstyle="round"/>
   <v:formulas/>
   <v:path arrowok="t" o:connecttype="custom" o:connectlocs="445380297,0;404890840,181451236;293545725,317539675;161956571,393144336;0,438507232"
    o:connectangles="0,0,0,0,0" textboxrect="0,0,264,174"/>
   <v:textbox style='mso-rotate-with-shape:t'/>
  </v:shape><v:shape id="Freeform_x0020_174" o:spid="_x0000_s12342" style='position:absolute;
   left:460.25pt;top:386.25pt;width:36.25pt;height:21pt;visibility:visible;
   mso-wrap-style:none;v-text-anchor:middle' coordsize="290,174" o:spt="100"
   adj="-11796480,,5400" path="m290,174v-28,-1,-55,-1,-84,-6c177,163,142,155,116,144,90,133,68,117,50,102,32,87,16,71,8,54,,37,3,11,2,e"
   filled="f" strokecolor="#66f">
   <v:stroke endarrow="open" joinstyle="round"/>
   <v:formulas/>
   <v:path arrowok="t" o:connecttype="custom" o:connectlocs="730845203,408786772;519152167,394689900;292338101,338305862;126007809,239633027;20161248,126864902;5040312,0"
    o:connectangles="0,0,0,0,0,0" textboxrect="0,0,290,174"/>
   <v:textbox style='mso-rotate-with-shape:t'/>
  </v:shape><v:shape id="Freeform_x0020_175" o:spid="_x0000_s12343" style='position:absolute;
   left:479pt;top:368.25pt;width:18.25pt;height:16.5pt;visibility:visible;
   mso-wrap-style:none;v-text-anchor:middle' coordsize="146,132" o:spt="100"
   adj="-11796480,,5400" path="m2,132c1,116,,101,8,84,16,67,34,43,50,30,66,17,88,11,104,6,120,1,133,,146,e"
   filled="f" strokecolor="#66f">
   <v:stroke endarrow="open" joinstyle="round"/>
   <v:formulas/>
   <v:path arrowok="t" o:connecttype="custom" o:connectlocs="5040312,332660570;20161248,211693126;126007809,75604677;262096240,15120937;367942758,0"
    o:connectangles="0,0,0,0,0" textboxrect="0,0,146,132"/>
   <v:textbox style='mso-rotate-with-shape:t'/>
  </v:shape></p:shaperange>
 <p:shaperange id="Freeform_x0020_176">
  <v:shape id="Freeform_x0020_176" o:spid="_x0000_s12344" style='position:absolute;
   left:460pt;top:354.5pt;width:37pt;height:28.5pt;visibility:visible;
   mso-wrap-style:none;v-text-anchor:middle' coordsize="146,132" o:spt="100"
   adj="-11796480,,5400" path="m2,132c1,116,,101,8,84,16,67,34,43,50,30,66,17,88,11,104,6,120,1,133,,146,e"
   filled="f" strokecolor="#f90">
   <v:stroke endarrow="open" joinstyle="round"/>
   <v:formulas/>
   <v:path arrowok="t" o:connecttype="custom" o:connectlocs="20717438,992483236;82869752,631580693;517935995,225563383;1077303635,45112132;1512369702,0"
    o:connectangles="0,0,0,0,0" textboxrect="0,0,146,132"/>
   <v:textbox style='mso-rotate-with-shape:t'/>
  </v:shape><v:shape id="Freeform_x0020_177" o:spid="_x0000_s12345" style='position:absolute;
   left:497.25pt;top:368.125pt;width:27pt;height:15.875pt;visibility:visible;
   mso-wrap-style:none;v-text-anchor:middle' coordsize="234,127" o:spt="100"
   adj="-11796480,,5400" path="m,1c10,,20,,36,1,52,2,75,2,96,7v21,5,50,16,66,24c178,39,183,45,192,55v9,10,17,24,24,36c223,103,228,115,234,127e"
   filled="f" strokecolor="#66f">
   <v:stroke endarrow="open" joinstyle="round"/>
   <v:formulas/>
   <v:path arrowok="t" o:connecttype="custom" o:connectlocs="0,2519356;77304903,2519356;206145949,17640258;347870585,78123862;412291899,138607473;463827997,229332900;502480437,320058279"
    o:connectangles="0,0,0,0,0,0,0" textboxrect="0,0,234,127"/>
   <v:textbox style='mso-rotate-with-shape:t'/>
  </v:shape><v:shape id="Freeform_x0020_178" o:spid="_x0000_s12346" style='position:absolute;
   left:497.75pt;top:386pt;width:39.75pt;height:35.25pt;visibility:visible;
   mso-wrap-style:none;v-text-anchor:middle' coordsize="264,174" o:spt="100"
   adj="-11796480,,5400" path="m264,v-5,25,-9,51,-24,72c225,93,198,112,174,126v-24,14,-49,22,-78,30c67,164,21,171,,174e"
   filled="f" strokecolor="#f90">
   <v:stroke endarrow="open" joinstyle="round"/>
   <v:formulas/>
   <v:path arrowok="t" o:connecttype="custom" o:connectlocs="965334189,0;877576905,476606634;636243895,834059720;351031168,1032647251;0,1151798226"
    o:connectangles="0,0,0,0,0" textboxrect="0,0,264,174"/>
   <v:textbox style='mso-rotate-with-shape:t'/>
  </v:shape><v:shape id="Freeform_x0020_179" o:spid="_x0000_s12347" style='position:absolute;
   left:445pt;top:386pt;width:51.25pt;height:35.25pt;visibility:visible;
   mso-wrap-style:none;v-text-anchor:middle' coordsize="290,174" o:spt="100"
   adj="-11796480,,5400" path="m290,174v-28,-1,-55,-1,-84,-6c177,163,142,155,116,144,90,133,68,117,50,102,32,87,16,71,8,54,,37,3,11,2,e"
   filled="f" strokecolor="#f90">
   <v:stroke endarrow="open" joinstyle="round"/>
   <v:formulas/>
   <v:path arrowok="t" o:connecttype="custom" o:connectlocs="1460821552,1151798226;1037687612,1112081234;584328537,953213267;251866145,675191753;40298141,357455659;10075096,0"
    o:connectangles="0,0,0,0,0,0" textboxrect="0,0,290,174"/>
   <v:textbox style='mso-rotate-with-shape:t'/>
  </v:shape></p:shaperange>
 <p:shaperange id="Freeform_x0020_180">
  <v:shape id="Freeform_x0020_180" o:spid="_x0000_s12348" style='position:absolute;
   left:444pt;top:342.25pt;width:52.75pt;height:42pt;visibility:visible;
   mso-wrap-style:none;v-text-anchor:middle' coordsize="146,132" o:spt="100"
   adj="-11796480,,5400" path="m2,132c1,116,,101,8,84,16,67,34,43,50,30,66,17,88,11,104,6,120,1,133,,146,e"
   filled="f" strokecolor="#9c0 [7]">
   <v:stroke endarrow="open" joinstyle="round"/>
   <v:formulas/>
   <v:path arrowok="t" o:connecttype="custom" o:connectlocs="42108916,2147483647;168435665,1371629889;1052727333,489867186;2147483647,97971827;2147483647,0"
    o:connectangles="0,0,0,0,0" textboxrect="0,0,146,132"/>
   <v:textbox style='mso-rotate-with-shape:t'/>
  </v:shape><v:shape id="Freeform_x0020_181" o:spid="_x0000_s12349" style='position:absolute;
   left:496pt;top:385.75pt;width:55.5pt;height:48.75pt;visibility:visible;
   mso-wrap-style:none;v-text-anchor:middle' coordsize="264,174" o:spt="100"
   adj="-11796480,,5400" path="m264,v-5,25,-9,51,-24,72c225,93,198,112,174,126v-24,14,-49,22,-78,30c67,164,21,171,,174e"
   filled="f" strokecolor="#9c0 [7]">
   <v:stroke endarrow="open" joinstyle="round"/>
   <v:formulas/>
   <v:path arrowok="t" o:connecttype="custom" o:connectlocs="1881869201,0;1710790971,911572510;1240322169,1595250170;684315754,1975072994;0,2147483647"
    o:connectangles="0,0,0,0,0" textboxrect="0,0,264,174"/>
   <v:textbox style='mso-rotate-with-shape:t'/>
  </v:shape><v:shape id="Freeform_x0020_182" o:spid="_x0000_s12350" style='position:absolute;
   left:498.5pt;top:342pt;width:53.25pt;height:42.5pt;visibility:visible;
   mso-wrap-style:none;v-text-anchor:middle' coordsize="540,448" o:spt="100"
   adj="-11796480,,5400" path="m,4c24,2,48,,78,4v30,4,70,14,102,24c212,38,236,45,270,64v34,19,83,51,114,78c415,169,436,195,456,226v20,31,36,74,48,102c516,356,522,374,528,394v6,20,10,44,12,54e"
   filled="f" strokecolor="#9c0 [7]">
   <v:stroke endarrow="open" joinstyle="round"/>
   <v:formulas/>
   <v:path arrowok="t" o:connecttype="custom" o:connectlocs="0,5805928;122335627,5805928;282313454,40642701;423470846,92898457;602269109,206119460;715194616,328048786;790477765,476105303;828119966,571907288;846940441,650290442"
    o:connectangles="0,0,0,0,0,0,0,0,0" textboxrect="0,0,540,448"/>
   <v:textbox style='mso-rotate-with-shape:t'/>
  </v:shape></p:shaperange>
 <p:shaperange id="Freeform_x0020_183">
  <v:shape id="Freeform_x0020_183" o:spid="_x0000_s12351" style='position:absolute;
   left:498.5pt;top:354.75pt;width:39pt;height:29.75pt;visibility:visible;
   mso-wrap-style:none;v-text-anchor:middle' coordsize="540,448" o:spt="100"
   adj="-11796480,,5400" path="m,4c24,2,48,,78,4v30,4,70,14,102,24c212,38,236,45,270,64v34,19,83,51,114,78c415,169,436,195,456,226v20,31,36,74,48,102c516,356,522,374,528,394v6,20,10,44,12,54e"
   filled="f" strokecolor="#f90">
   <v:stroke endarrow="open" joinstyle="round"/>
   <v:formulas/>
   <v:path arrowok="t" o:connecttype="custom" o:connectlocs="0,2844651;65620828,2844651;151433378,19915089;227150038,45520323;323057559,100998188;383630887,160743462;424013412,233291799;444204215,280234856;454300076,318642274"
    o:connectangles="0,0,0,0,0,0,0,0,0" textboxrect="0,0,540,448"/>
   <v:textbox style='mso-rotate-with-shape:t'/>
  </v:shape><v:shape id="Text_x0020_Box_x0020_184" o:spid="_x0000_s12352"
   type="#_x0000_t202" style='position:absolute;left:380.625pt;top:325.875pt;
   width:105.5pt;height:28.75pt;visibility:visible;mso-wrap-style:none'
   filled="f" stroked="f">
   <v:textbox style='mso-rotate-with-shape:t;mso-fit-shape-to-text:t'/>
  </v:shape><v:shape id="Text_x0020_Box_x0020_185" o:spid="_x0000_s12353"
   type="#_x0000_t202" style='position:absolute;left:505.125pt;top:326.375pt;
   width:84pt;height:18pt;visibility:visible;mso-wrap-style:none' filled="f"
   stroked="f">
   <v:textbox style='mso-rotate-with-shape:t;mso-fit-shape-to-text:t'/>
  </v:shape><v:shape id="Text_x0020_Box_x0020_186" o:spid="_x0000_s12354"
   type="#_x0000_t202" style='position:absolute;left:504.5pt;top:428.875pt;
   width:82pt;height:18pt;visibility:visible;mso-wrap-style:none' filled="f"
   stroked="f">
   <v:textbox style='mso-rotate-with-shape:t;mso-fit-shape-to-text:t'/>
  </v:shape><v:shape id="Text_x0020_Box_x0020_187" o:spid="_x0000_s12355"
   type="#_x0000_t202" style='position:absolute;left:407.375pt;top:404.875pt;
   width:31.5pt;height:18pt;visibility:visible;mso-wrap-style:none' filled="f"
   stroked="f">
   <v:textbox style='mso-rotate-with-shape:t;mso-fit-shape-to-text:t'/>
  </v:shape></p:shaperange>
 <p:shaperange id="Oval_x0020_188">
  <v:oval id="Oval_x0020_188" o:spid="_x0000_s12356" style='position:absolute;
   left:446.25pt;top:434.25pt;width:24.75pt;height:25.5pt;visibility:visible;
   mso-wrap-style:none;v-text-anchor:middle' fillcolor="#e0e0e0" strokecolor="#d7d7d7">
   <v:textbox style='mso-rotate-with-shape:t'/>
  </v:oval></p:shaperange>
 <p:shaperange id="Oval_x0020_189">
  <v:oval id="Oval_x0020_189" o:spid="_x0000_s12357" style='position:absolute;
   left:455.25pt;top:442.5pt;width:6.875pt;height:8.25pt;visibility:visible;
   mso-wrap-style:none;v-text-anchor:middle' fillcolor="white [0]"
   strokecolor="silver">
   <v:textbox style='mso-rotate-with-shape:t'/>
  </v:oval><v:shape id="Text_x0020_Box_x0020_190" o:spid="_x0000_s12358"
   type="#_x0000_t202" style='position:absolute;left:432.5pt;top:428.875pt;
   width:50.5pt;height:18pt;visibility:visible;mso-wrap-style:none' filled="f"
   stroked="f">
   <v:textbox style='mso-rotate-with-shape:t;mso-fit-shape-to-text:t'/>
  </v:shape><v:rect id="Rectangle_x0020_191" o:spid="_x0000_s12359" style='position:absolute;
   left:443.625pt;top:445.875pt;width:31pt;height:18pt;visibility:visible;
   mso-wrap-style:none' filled="f" stroked="f">
   <v:textbox style='mso-rotate-with-shape:t;mso-fit-shape-to-text:t'/>
  </v:rect><v:shape id="Text_x0020_Box_x0020_192" o:spid="_x0000_s12360"
   type="#_x0000_t202" style='position:absolute;left:180.875pt;top:277.625pt;
   width:55.375pt;height:19.25pt;visibility:visible;mso-wrap-style:none'
   filled="f" stroked="f">
   <v:textbox style='mso-rotate-with-shape:t;mso-fit-shape-to-text:t'/>
  </v:shape><v:shape id="Text_x0020_Box_x0020_193" o:spid="_x0000_s12361"
   type="#_x0000_t202" style='position:absolute;left:409.75pt;top:279pt;
   width:131.375pt;height:19.25pt;visibility:visible;mso-wrap-style:none'
   filled="f" stroked="f">
   <v:textbox style='mso-rotate-with-shape:t;mso-fit-shape-to-text:t'/>
  </v:shape><v:shape id="Text_x0020_Box_x0020_194" o:spid="_x0000_s12362"
   type="#_x0000_t202" style='position:absolute;left:186.875pt;top:457.625pt;
   width:64.5pt;height:19.25pt;visibility:visible;mso-wrap-style:none'
   filled="f" stroked="f">
   <v:textbox style='mso-rotate-with-shape:t;mso-fit-shape-to-text:t'/>
  </v:shape><v:shape id="Text_x0020_Box_x0020_195" o:spid="_x0000_s12363"
   type="#_x0000_t202" style='position:absolute;left:474.875pt;top:462.75pt;
   width:47.625pt;height:19.25pt;visibility:visible;mso-wrap-style:none'
   filled="f" stroked="f">
   <v:textbox style='mso-rotate-with-shape:t;mso-fit-shape-to-text:t'/>
  </v:shape></p:shaperange>
 <p:shaperange id="Group_x0020_196">
  <v:group id="Group_x0020_196" o:spid="_x0000_s12364" style='position:absolute;
   left:17.75pt;top:125.75pt;width:42pt;height:373.5pt' coordorigin="2200,832"
   coordsize="336,2988">
   <v:rect id="Rectangle_x0020_197" o:spid="_x0000_s12365" style='position:absolute;
    left:2200;top:832;width:246;height:2988;visibility:visible;
    mso-wrap-style:none;v-text-anchor:middle' fillcolor="#f90" strokecolor="#f90">
    <v:textbox style='mso-rotate-with-shape:t'/>
   </v:rect><v:rect id="Rectangle_x0020_198" o:spid="_x0000_s12366" style='position:absolute;
    left:2452;top:1036;width:84;height:330;visibility:visible;mso-wrap-style:none;
    v-text-anchor:middle' fillcolor="#ddd" strokecolor="#ddd">
    <v:textbox style='mso-rotate-with-shape:t'/>
   </v:rect><v:shape id="Text_x0020_Box_x0020_199" o:spid="_x0000_s12367"
    type="#_x0000_t202" style='position:absolute;left:2214;top:1775;width:203;
    height:1264;visibility:visible;mso-wrap-style:none' filled="f" stroked="f">
    <v:textbox style='mso-rotate-with-shape:t;mso-fit-shape-to-text:t'/>
   </v:shape><v:rect id="Rectangle_x0020_200" o:spid="_x0000_s12368" style='position:absolute;
    left:2445;top:1413;width:84;height:330;visibility:visible;mso-wrap-style:none;
    v-text-anchor:middle' fillcolor="#ddd" strokecolor="#ddd">
    <v:textbox style='mso-rotate-with-shape:t'/>
   </v:rect><v:rect id="Rectangle_x0020_201" o:spid="_x0000_s12369" style='position:absolute;
    left:2445;top:1785;width:84;height:330;visibility:visible;mso-wrap-style:none;
    v-text-anchor:middle' fillcolor="#f90" strokecolor="#f90">
    <v:textbox style='mso-rotate-with-shape:t'/>
   </v:rect><v:rect id="Rectangle_x0020_202" o:spid="_x0000_s12370" style='position:absolute;
    left:2451;top:2157;width:84;height:330;visibility:visible;mso-wrap-style:none;
    v-text-anchor:middle' fillcolor="#ddd" strokecolor="#ddd">
    <v:textbox style='mso-rotate-with-shape:t'/>
   </v:rect><v:rect id="Rectangle_x0020_203" o:spid="_x0000_s12371" style='position:absolute;
    left:2451;top:2535;width:84;height:330;visibility:visible;mso-wrap-style:none;
    v-text-anchor:middle' fillcolor="#ddd" strokecolor="#ddd">
    <v:textbox style='mso-rotate-with-shape:t'/>
   </v:rect><v:rect id="Rectangle_x0020_204" o:spid="_x0000_s12372" style='position:absolute;
    left:2451;top:2907;width:84;height:330;visibility:visible;mso-wrap-style:none;
    v-text-anchor:middle' fillcolor="#ddd" strokecolor="#ddd">
    <v:textbox style='mso-rotate-with-shape:t'/>
   </v:rect><v:rect id="Rectangle_x0020_205" o:spid="_x0000_s12373" style='position:absolute;
    left:2451;top:3285;width:84;height:330;visibility:visible;mso-wrap-style:none;
    v-text-anchor:middle' fillcolor="#ddd" strokecolor="#ddd">
    <v:textbox style='mso-rotate-with-shape:t'/>
   </v:rect></v:group><v:rect id="Rectangle_x0020_9" o:spid="_x0000_s12394"
   style='position:absolute;left:581.75pt;top:499pt;width:90.25pt;height:31.25pt;
   visibility:visible;mso-wrap-style:none;v-text-anchor:middle' filled="f"
   stroked="f">
   <v:textbox style='mso-rotate-with-shape:t;mso-fit-shape-to-text:t'/>
  </v:rect></p:shaperange>
</xml>